{
  "$schema": "https://developer.microsoft.com/en-us/json-schemas/teams/v1.7/MicrosoftTeams.Localization.schema.json",
  "name.short": "Etapas",
  "name.full": "Etapas do Power App",
  "description.short": "Monitore seu trabalho com controle eficaz, status da equipe e log de atividades",
  "description.full": "Planeje, rastreie e priorize a capacidade de trabalho da equipe em todos os projetos em um local centralizado. Veja o status da equipe e as atualizações de itens de trabalho para estar ciente do andamento do trabalho no momento e tome as medidas necessárias. Gerencie facilmente vários projetos no aplicativo para evitar a troca de plataformas. O aplicativo pode ser facilmente estendido com o Microsoft Power Platform para atender às necessidades de sua organização.",
  "activities.activityTypes[0].description": "O aplicativo requer atividade de parâmetros",
  "activities.activityTypes[1].description": "Atividade de instalação bem-sucedida",
  "activities.activityTypes[2].description": "Falha na atividade de instalação",
  "activities.activityTypes[0].templateText": "{actor} requer informações adicionais.",
  "activities.activityTypes[1].templateText": "Êxito ao instalar {actor}.",
  "activities.activityTypes[2].templateText": "Falha ao instalar {actor}."
}