{
  "$schema": "https://developer.microsoft.com/en-us/json-schemas/teams/v1.7/MicrosoftTeams.Localization.schema.json",
  "name.short": "Bulletins",
  "name.full": "Power App für Bulletins",
  "description.short": "Alle Unternehmenskommunikationsbeiträge an einem zentralen Ort lesen",
  "description.full": "Informieren Sie sich über alle Kommunikationsbeiträge, Übertragungen und Ankündigungen des Unternehmens in einer einfach zu nutzenden Erfahrung in Microsoft Teams. Passen Sie Beitragskategorien nach Bedarf an, und versehen Sie Beiträge mit Lesezeichen, um sie später aufrufen zu können. Greifen Sie auf unternehmensbezogene wichtige FAQ und Links zu, um schnell Antworten auf Ihre Fragen zu erhalten. Die App lässt sich mit Microsoft Power Platform einfach erweitern, um die spezifischen Anforderungen Ihrer Organisation zu erfüllen.",
  "activities.activityTypes[0].description": "Aktivität „App erfordert Parameter“",
  "activities.activityTypes[0].templateText": "{actor} erfordert Zusatzinformationen.",
  "activities.activityTypes[1].description": "Aktivität „Installation erfolgreich“",
  "activities.activityTypes[1].templateText": "{actor} erfolgreich installiert.",
  "activities.activityTypes[2].description": "Aktivität „Fehler bei Installation“",
  "activities.activityTypes[2].templateText": "Fehler beim Installieren von {actor}."
}