{
  "$schema": "https://developer.microsoft.com/en-us/json-schemas/teams/v1.7/MicrosoftTeams.Localization.schema.json",
  "name.short": "Profile+",
  "name.full": "Profile+ Power Apps",
  "description.short": "組織のユーザーの詳細を確認し、価値のあるつながりを作成します",
  "description.full": "Profile+ を使用すると、組織で誰が何を行っているかすばやく検索し、オープンなポジションを確認できます。名前、プロジェクト、および専門知識で検索する機能を使用して、同じ考えを持つユーザーが探し合ってつながる新たな機会を作ることができます。アプリのプロファイル カードは柔軟性が高く、Microsoft Teams 内から簡単に更新できます。自分が最も重要視することを強調し、現在のプロジェクトをリストして、さらにビデオを追加して個性を表現します。会議や共同作業を行う相手を見つけたら、簡単にチャットで自己紹介したり、その人に電話をしたり、Microsoft Teams 会議のスケジュールを設定できます。注意: このアプリを Microsoft Power Platform で簡単に拡張して、組織のニーズを満たすことができます。",
  "activities.activityTypes[0].description": "アプリにはパラメーターの活動が必要です",
  "activities.activityTypes[1].description": "インストール成功の活動",
  "activities.activityTypes[2].description": "インストール失敗の活動",
  "activities.activityTypes[0].templateText": "{actor} には追加情報が必要です。",
  "activities.activityTypes[1].templateText": "{actor} が正常にインストールされました。",
  "activities.activityTypes[2].templateText": "{actor} のインストールに失敗しました。"
}