[
  {
    "CdsFCBContext": "{\"FileType\":true,\"ImageExternalStorage\":true}",
    "EntitySetName": "msft_discussionappsettings",
    "IsHidden": false,
    "IsSampleData": false,
    "IsWritable": true,
    "LogicalName": "msft_discussionappsetting",
    "MaxGetRowsCount": 500,
    "Name": "Discussion App Settings",
    "NativeCDSDataSourceInfoNameMapping": {
      "_ownerid_value": "Owner",
      "createdby": "Created By",
      "createdon": "Created On",
      "createdonbehalfby": "Created By (Delegate)",
      "importsequencenumber": "Import Sequence Number",
      "modifiedby": "Modified By",
      "modifiedon": "Modified On",
      "modifiedonbehalfby": "Modified By (Delegate)",
      "msft_discussionappsetting_AsyncOperations": "System Jobs",
      "msft_discussionappsetting_BulkDeleteFailures": "Bulk Delete Failures",
      "msft_discussionappsetting_DuplicateBaseRecord": "Duplicate Records (msft_discussionappsetting_DuplicateBaseRecord)",
      "msft_discussionappsetting_DuplicateMatchingRecord": "Duplicate Records (msft_discussionappsetting_DuplicateMatchingRecord)",
      "msft_discussionappsetting_MailboxTrackingFolders": "Mailbox Auto Tracking Folders",
      "msft_discussionappsetting_PrincipalObjectAttributeAccesses": "Field Sharing",
      "msft_discussionappsetting_ProcessSession": "Process Sessions",
      "msft_discussionappsetting_SyncErrors": "Sync Errors",
      "msft_discussionappsettingid": "Discussion App Setting",
      "msft_name": "Name",
      "msft_teamid": "Team ID",
      "overriddencreatedon": "Record Created On",
      "owningbusinessunit": "Owning Business Unit",
      "owningteam": "Owning Team",
      "owninguser": "Owning User",
      "statecode": "Status",
      "statuscode": "Status Reason",
      "timezoneruleversionnumber": "Time Zone Rule Version Number",
      "utcconversiontimezonecode": "UTC Conversion Time Zone Code",
      "versionnumber": "Version Number"
    },
    "PreferredName": "Discussion App Settings",
    "Type": "NativeCDSDataSourceInfo"
  },
  {
    "DisplayName": "Discussion App Settings (Views)",
    "Name": "_msft_discussionappsetting_views",
    "RelatedEntityName": "Discussion App Settings",
    "TrimmedViewName": true,
    "Type": "ViewInfo",
    "ViewInfoNameMapping": {
      "090c54a7-fe34-4638-992d-b458431567ba": "Active Discussion App Settings",
      "412ef3dd-0617-492c-b5dc-570f034504b8": "Discussion App Setting Lookup View",
      "7c78a4bb-999c-47f0-a291-5a6c9274ef22": "Discussion App Setting Advanced Find View",
      "d7641f1d-0cb2-43ca-8268-f02b020a430e": "Inactive Discussion App Settings",
      "e52fdc82-9322-4843-8509-936eb2419bbf": "Discussion App Setting Associated View"
    }
  },
  {
    "DisplayName": "Status (Discussion App Settings)",
    "Name": "msft_discussionappsetting_statecode",
    "OptionSetInfoNameMapping": {
      "0": "Active",
      "1": "Inactive"
    },
    "OptionSetIsBooleanValued": false,
    "OptionSetIsGlobal": false,
    "OptionSetReference": {
      "OptionSetReferenceItem0": {
        "OptionSetReferenceColumnName": "statecode",
        "OptionSetReferenceEntityName": "Discussion App Settings"
      }
    },
    "OptionSetTypeKey": "StateType",
    "RelatedColumnInvariantName": "statecode",
    "RelatedEntityName": "Discussion App Settings",
    "Type": "OptionSetInfo"
  },
  {
    "DisplayName": "Status Reason (Discussion App Settings)",
    "Name": "msft_discussionappsetting_statuscode",
    "OptionSetInfoNameMapping": {
      "1": "Active",
      "2": "Inactive"
    },
    "OptionSetIsBooleanValued": false,
    "OptionSetIsGlobal": false,
    "OptionSetReference": {
      "OptionSetReferenceItem0": {
        "OptionSetReferenceColumnName": "statuscode",
        "OptionSetReferenceEntityName": "Discussion App Settings"
      }
    },
    "OptionSetTypeKey": "StatusType",
    "RelatedColumnInvariantName": "statuscode",
    "RelatedEntityName": "Discussion App Settings",
    "Type": "OptionSetInfo"
  }
]